LICENSE
MANIFEST.in
NOTICE
README.rst
setup.cfg
setup.py
agentsmith/__init__.py
agentsmith/__main__.py
agentsmith/application.py
agentsmith/meta.py
agentsmith/monitor.py
agentsmith/units.py
agentsmith.egg-info/PKG-INFO
agentsmith.egg-info/SOURCES.txt
agentsmith.egg-info/dependency_links.txt
agentsmith.egg-info/entry_points.txt
agentsmith.egg-info/requires.txt
agentsmith.egg-info/top_level.txt
agentsmith/controls/__init__.py
agentsmith/controls/data.py
agentsmith/controls/overview.py
agentsmith/controls/server.py